pygochook/__init__.py
pygochook/main.py
pygochook-0.0.2.dist-info/LICENSE.txt
pygochook-0.0.2.dist-info/METADATA
pygochook-0.0.2.dist-info/WHEEL
pygochook-0.0.2.dist-info/top_level.txt
pygochook-0.0.2.dist-info/RECORD
