Metadata-Version: 2.1
Name: pygochook
Version: 0.0.2
Summary: A simple python package to send messages to Google Chats via Webhooks
Home-page: https://github.com/Lars147/pygochook
Author: Lars Heinen
Author-email: larsheinen@gmail.com
License: UNKNOWN
Platform: UNKNOWN
Classifier: Programming Language :: Python :: 3
Classifier: License :: OSI Approved :: MIT License
Classifier: Operating System :: OS Independent
Requires-Python: >=3.7
Requires-Dist: aiohttp (>=3.7)
